topsis_tanya_102303077/__init__.py
topsis_tanya_102303077/topsis.py
topsis_tanya_102303077-1.0.3.dist-info/LICENSE
topsis_tanya_102303077-1.0.3.dist-info/METADATA
topsis_tanya_102303077-1.0.3.dist-info/WHEEL
topsis_tanya_102303077-1.0.3.dist-info/entry_points.txt
topsis_tanya_102303077-1.0.3.dist-info/top_level.txt
topsis_tanya_102303077-1.0.3.dist-info/RECORD
