Metadata-Version: 2.2
Name: Topsis-Tanya-102303077
Version: 1.0.3
Summary: A Python package for TOPSIS decision making
Author: Tanya Mediratta
Author-email: tanya@example.com
License: MIT
Classifier: License :: OSI Approved :: MIT License
Classifier: Programming Language :: Python :: 3
Classifier: Operating System :: OS Independent
Requires-Python: >=3.6
License-File: LICENSE
Requires-Dist: numpy
Requires-Dist: pandas
Dynamic: author
Dynamic: author-email
Dynamic: classifier
Dynamic: description
Dynamic: description-content-type
Dynamic: license
Dynamic: requires-dist
Dynamic: requires-python
Dynamic: summary
